media_downloader/__init__.py
media_downloader/__main__.py
media_downloader/mcp_config.json
media_downloader/media_downloader.py
media_downloader/media_downloader_agent.py
media_downloader/media_downloader_mcp.py
media_downloader/middlewares.py
media_downloader/utils.py
media_downloader/skills/media-downloader-collection/SKILL.md
media_downloader-2.1.37.dist-info/licenses/LICENSE
tests/test_mcp.py
media_downloader-2.1.37.dist-info/METADATA
media_downloader-2.1.37.dist-info/WHEEL
media_downloader-2.1.37.dist-info/entry_points.txt
media_downloader-2.1.37.dist-info/top_level.txt
media_downloader-2.1.37.dist-info/RECORD
